skrub/VERSION.txt
skrub/__init__.py
skrub/_agg_joiner.py
skrub/_apply_to_cols.py
skrub/_apply_to_frame.py
skrub/_check_input.py
skrub/_clean_categories.py
skrub/_clean_null_strings.py
skrub/_column_associations.py
skrub/_config.py
skrub/_datetime_encoder.py
skrub/_deduplicate.py
skrub/_dispatch.py
skrub/_drop_uninformative.py
skrub/_fast_hash.py
skrub/_fuzzy_join.py
skrub/_gap_encoder.py
skrub/_interpolation_joiner.py
skrub/_join_utils.py
skrub/_joiner.py
skrub/_matching.py
skrub/_minhash_encoder.py
skrub/_multi_agg_joiner.py
skrub/_scaling_factor.py
skrub/_select_cols.py
skrub/_similarity_encoder.py
skrub/_sklearn_compat.py
skrub/_squashing_scaler.py
skrub/_string_distances.py
skrub/_string_encoder.py
skrub/_table_vectorizer.py
skrub/_tabular_pipeline.py
skrub/_text_encoder.py
skrub/_to_categorical.py
skrub/_to_datetime.py
skrub/_to_float.py
skrub/_to_str.py
skrub/_utils.py
skrub/_wrap_transformer.py
skrub/conftest.py
skrub/_data_ops/__init__.py
skrub/_data_ops/_choosing.py
skrub/_data_ops/_data_ops.py
skrub/_data_ops/_data_ops.pyi
skrub/_data_ops/_estimator.py
skrub/_data_ops/_evaluation.py
skrub/_data_ops/_inspection.py
skrub/_data_ops/_optuna.py
skrub/_data_ops/_parallel_coord.py
skrub/_data_ops/_skrub_namespace.py
skrub/_data_ops/_subsampling.py
skrub/_data_ops/_utils.py
skrub/_data_ops/tests/__init__.py
skrub/_data_ops/tests/test_choosing.py
skrub/_data_ops/tests/test_data_ops.py
skrub/_data_ops/tests/test_deferred.py
skrub/_data_ops/tests/test_errors.py
skrub/_data_ops/tests/test_estimators.py
skrub/_data_ops/tests/test_evaluation.py
skrub/_data_ops/tests/test_inspection.py
skrub/_data_ops/tests/test_interactive_features.py
skrub/_data_ops/tests/test_parallel_coord.py
skrub/_data_ops/tests/test_subsampling.py
skrub/_data_ops/tests/test_utils.py
skrub/_dataframe/__init__.py
skrub/_dataframe/_common.py
skrub/_dataframe/tests/__init__.py
skrub/_dataframe/tests/test_common.py
skrub/_reporting/README.rst
skrub/_reporting/__init__.py
skrub/_reporting/_html.py
skrub-0.7.1.dist-info/licenses/LICENSE.txt
skrub-0.7.1.dist-info/METADATA
skrub-0.7.1.dist-info/WHEEL
skrub-0.7.1.dist-info/top_level.txt
skrub-0.7.1.dist-info/RECORD
