Metadata-Version: 2.4
Name: skrub
Version: 0.7.1
Summary: Machine learning with dataframes
Author: Riccardo Cappuzzo, Jerome Dockes, Guillaume Lemaitre, Vincent Maladiere, Gael Varoquaux
License-Expression: BSD-3-Clause
Project-URL: Homepage, https://skrub-data.org/
Project-URL: Source, https://github.com/skrub-data/skrub
Project-URL: Issues, https://github.com/skrub-data/skrub/issues
Classifier: Development Status :: 5 - Production/Stable
Classifier: Environment :: Console
Classifier: Intended Audience :: Science/Research
Classifier: Operating System :: OS Independent
Classifier: Programming Language :: Python :: 3.10
Classifier: Programming Language :: Python :: 3.11
Classifier: Programming Language :: Python :: 3.12
Classifier: Programming Language :: Python :: 3.13
Classifier: Programming Language :: Python :: 3.14
Classifier: Topic :: Scientific/Engineering
Classifier: Topic :: Software Development :: Libraries
Requires-Python: >=3.10
License-File: LICENSE.txt
Requires-Dist: numpy>=1.23.5
Requires-Dist: pandas>=1.5.3
Requires-Dist: scikit-learn>=1.4.2
Requires-Dist: scipy>=1.9.3
Requires-Dist: jinja2>=3.1.2
Requires-Dist: matplotlib>=3.4.3
Requires-Dist: requests>=2.27.1
Requires-Dist: pydot
Provides-Extra: dev
Requires-Dist: ipykernel; extra == "dev"
Requires-Dist: ipython; extra == "dev"
Requires-Dist: jupyterlab; extra == "dev"
Requires-Dist: jupyterlite-sphinx; extra == "dev"
Requires-Dist: jupyterlite-pyodide-kernel; extra == "dev"
Requires-Dist: numpydoc; extra == "dev"
Requires-Dist: pydata-sphinx-theme; extra == "dev"
Requires-Dist: seaborn; extra == "dev"
Requires-Dist: sphinx<9; extra == "dev"
Requires-Dist: sphinx-copybutton; extra == "dev"
Requires-Dist: sphinx-gallery; extra == "dev"
Requires-Dist: sphinxext-opengraph; extra == "dev"
Requires-Dist: sphinx-autosummary-accessors; extra == "dev"
Requires-Dist: statsmodels; extra == "dev"
Requires-Dist: black==23.3.0; extra == "dev"
Requires-Dist: ruff==0.14.2; extra == "dev"
Requires-Dist: pre-commit; extra == "dev"
Requires-Dist: pytest; extra == "dev"
Requires-Dist: pytest-cov; extra == "dev"
Requires-Dist: pytest-xdist; extra == "dev"
Requires-Dist: pyarrow; extra == "dev"
Requires-Dist: polars; extra == "dev"
Requires-Dist: plotly; extra == "dev"
Requires-Dist: optuna; extra == "dev"
Provides-Extra: transformers
Requires-Dist: sentence-transformers; extra == "transformers"
Dynamic: license-file
